yamlup/__init__.py
yamlup/__main__.py
yamlup/cli.py
yamlup/schema.py
yaml_setup-0.1.2.dist-info/entry_points.txt
yaml_setup-0.1.2.dist-info/METADATA
yaml_setup-0.1.2.dist-info/WHEEL
yaml_setup-0.1.2.dist-info/RECORD
